BayesMonSTR/BayesMonSTR.py
BayesMonSTR/__init__.py
BayesMonSTR/example.py
bayesmonstr-0.0.1.dist-info/METADATA
bayesmonstr-0.0.1.dist-info/WHEEL
bayesmonstr-0.0.1.dist-info/entry_points.txt
bayesmonstr-0.0.1.dist-info/RECORD
